wrangle_pypes/__init__.py
wrangle_pypes/pipeline.py
wrangle_pypes/transformations.py
wrangle_pypes-0.3.dist-info/LICENSE
wrangle_pypes-0.3.dist-info/METADATA
wrangle_pypes-0.3.dist-info/WHEEL
wrangle_pypes-0.3.dist-info/top_level.txt
wrangle_pypes-0.3.dist-info/RECORD
