Metadata-Version: 2.1
Name: wrangle-pypes
Version: 0.3
Summary: Easy, model based data wrangling.
Home-page: https://github.com/tim-fi/wrangle_pypes
Author: Tim Fischer
Author-email: tim.fischer98@hotmail.com
License: MIT
Platform: UNKNOWN
Classifier: Programming Language :: Python :: 3
